paillierlib/__init__.py
paillierlib/paillier.py
paillierlib/test_paillier.py
paillierlib/utils.py
paillierlib-0.0.1.dist-info/METADATA
paillierlib-0.0.1.dist-info/RECORD
paillierlib-0.0.1.dist-info/WHEEL
paillierlib-0.0.1.dist-info/top_level.txt
