Metadata-Version: 2.1
Name: paillierlib
Version: 0.0.1
Summary: A simple implementation of the Paillier cryptosystem
Home-page: https://github.com/carltonshepherd/paillier-lib
Author: Carlton Shepherd
Author-email: carlton@linux.com
License: UNKNOWN
Keywords: encryption,decryption,homomorphic,crypto,cryptography,security,privacy
Platform: UNKNOWN
Classifier: Programming Language :: Python :: 3
Classifier: License :: OSI Approved :: MIT License
Classifier: Operating System :: OS Independent
Classifier: Topic :: Security :: Cryptography
Classifier: Intended Audience :: Science/Research
Classifier: Development Status :: 3 - Alpha
Requires-Dist: gmpy2 (>=2.0.0)
